{
  "url": "https://www.wix.com/website-template/view/html/1929",
  "requestedUrl": "https://www.wix.com/website-template/view/html/1929",
  "timestamp": 1628824329296,
  "ranks": {
    "hundos": 361,
    "performance": 360,
    "accessibility": 126,
    "cumulative": 359
  },
  "lighthouse": {
    "version": "8.2.0",
    "performance": 0.37,
    "accessibility": 0.69,
    "bestPractices": 0.8,
    "seo": 1,
    "total": 286
  },
  "firstContentfulPaint": 3412.001,
  "firstMeaningfulPaint": 3412.001,
  "speedIndex": 6676.1819772775025,
  "largestContentfulPaint": 6671.933999999999,
  "totalBlockingTime": 767,
  "cumulativeLayoutShift": 0.001850499754749624,
  "timeToInteractive": 17958.871,
  "maxPotentialFirstInputDelay": 327,
  "timeToFirstByte": 132.85999999999999,
  "weight": {
    "summary": "183 requests • 2,250 KiB",
    "total": 2304315,
    "image": 385935,
    "imageCount": 18,
    "script": 1456559,
    "scriptCount": 81,
    "document": 115774,
    "font": 109122,
    "fontCount": 4,
    "stylesheet": 54833,
    "stylesheetCount": 10,
    "thirdParty": 2051612,
    "thirdPartyCount": 147
  },
  "run": {
    "number": 3,
    "total": 3
  },
  "axe": {
    "error": "{}"
  }
}